openapscontrib.glucosetools-1.0.0-py2.7-nspkg.pth
openapscontrib/glucosetools/__init__.py
openapscontrib/glucosetools/glucose.py
openapscontrib/glucosetools/version.py
openapscontrib.glucosetools-1.0.0.dist-info/DESCRIPTION.rst
openapscontrib.glucosetools-1.0.0.dist-info/METADATA
openapscontrib.glucosetools-1.0.0.dist-info/metadata.json
openapscontrib.glucosetools-1.0.0.dist-info/namespace_packages.txt
openapscontrib.glucosetools-1.0.0.dist-info/RECORD
openapscontrib.glucosetools-1.0.0.dist-info/top_level.txt
openapscontrib.glucosetools-1.0.0.dist-info/WHEEL
