Metadata-Version: 2.0
Name: openapscontrib.glucosetools
Version: 1.0.0
Summary: openaps glucosetools plugin
Home-page: http://github.com/loudnate/openaps-glucosetools
Author: Nathan Racklyeft
Author-email: loudnate+pypi@gmail.com
License: MIT
Download-URL: http://pypi.python.org/pypi/openapscontrib.glucosetools
Platform: any
Classifier: Development Status :: 3 - Alpha
Classifier: Environment :: Console
Classifier: Intended Audience :: Developers
Classifier: License :: OSI Approved :: MIT License
Classifier: Operating System :: OS Independent
Classifier: Programming Language :: Python :: 2.7
Classifier: Topic :: Documentation
Classifier: Topic :: Utilities
Requires-Dist: openaps
